calfpy/__init__.py
calfpy/methods.py
calfpy-1.20.1.dist-info/LICENSE.txt
calfpy-1.20.1.dist-info/METADATA
calfpy-1.20.1.dist-info/WHEEL
calfpy-1.20.1.dist-info/top_level.txt
calfpy-1.20.1.dist-info/RECORD
