Metadata-Version: 2.1
Name: calfpy
Version: 1.20.1
Summary: Contains greedy algorithms for coarse approximation linear functions.
Home-page: https://github.com/jorufo/CALF_Python
Author: John Ford, Clark Jeffries, Diana Perkins
Author-email: JoRuFo@gmail.com
Project-URL: Bug Tracker, https://github.com/jorufo/CALF_Python/issues
Classifier: Programming Language :: Python :: 3
Classifier: License :: OSI Approved :: MIT License
Classifier: Operating System :: OS Independent
Requires-Python: >=3.6
License-File: LICENSE.txt
Requires-Dist: numpy (<=1.23.0,>=1.20.2)
Requires-Dist: pandas (<=1.5.2,>=1.2.4)
Requires-Dist: plotnine (==0.10.0)
Requires-Dist: scipy (<=1.9.3,>=1.6.3)
